PyForks/__init__.py
PyForks/events.py
PyForks/exceptions.py
PyForks/lookups.py
PyForks/regions.py
PyForks/trailforks.py
PyForks/trails.py
PyForks/utilities.py
PyForks/data/region_data.parquet
PyForks-1.0.0.dist-info/LICENSE
PyForks-1.0.0.dist-info/METADATA
PyForks-1.0.0.dist-info/WHEEL
PyForks-1.0.0.dist-info/top_level.txt
PyForks-1.0.0.dist-info/RECORD
