Metadata-Version: 2.1
Name: PyForks
Version: 1.0.0
Summary: Python library for the Trailforks API
Home-page: http://pypi.python.org/pypi/PyForks/
Author: Joshua Faust
Author-email: josh@mn-mtb.com
License: LICENSE.txt
Project-URL: Bug Reports, https://github.com/MN-MTB/PyForks/issues
Project-URL: Funding, https://account.venmo.com/u/mnmtb
Project-URL: Source, https://github.com/MN-MTB/PyForks/PyForks
Project-URL: Documentation, https://pyforks.mn-mtb.com
License-File: LICENSE
Requires-Dist: requests
